[
    {
        "caption": "a woman is peeling a potato",
        "id": "ScdUht-pM6s_53_63.avi"
    },
    {
        "caption": "a man is riding a skateboard",
        "id": "wkgGxsuNVSg_34_41.avi"
    },
    {
        "caption": "a woman is doing a dance on a stage",
        "id": "BtQtRGI0F2Q_15_20.avi"
    },
    {
        "caption": "a monkey is being held a dogs tail",
        "id": "k06Ge9ANKM8_5_16.avi"
    },
    {
        "caption": "a boy is skating",
        "id": "sZf3VDsdDPM_107_114.avi"
    },
    {
        "caption": "a cat is playing with a ferret",
        "id": "shPymuahrsc_5_12.avi"
    },
    {
        "caption": "a baby is laughing",
        "id": "XOAgUVVwKEA_8_20.avi"
    },
    {
        "caption": "a baby panda is climbing logs",
        "id": "ufFT2BWh3BQ_0_8.avi"
    },
    {
        "caption": "a man is walking on a rope",
        "id": "5YJaS2Eswg0_22_26.avi"
    },
    {
        "caption": "a woman is washing a bowl",
        "id": "lw7pTwpx0K0_38_48.avi"
    },
    {
        "caption": "a woman is cutting chicken",
        "id": "UbmZAe5u5FI_132_141.avi"
    },
    {
        "caption": "a man is riding a mini red colored scooter down the road in a pan",
        "id": "xCFCXzDUGjY_5_9.avi"
    },
    {
        "caption": "a man is firing on a steel plate from behind it target",
        "id": "He7Ge7Sogrk_47_70.avi"
    },
    {
        "caption": "a man is removing something from a package",
        "id": "tJHUH9tpqPg_113_118.avi"
    },
    {
        "caption": "a man is cutting a piece of carpet with a knife",
        "id": "n016q1w8Q30_2_11.avi"
    },
    {
        "caption": "a man is pushing a small garden tiller",
        "id": "RjpbFlOHFps_8_25.avi"
    },
    {
        "caption": "a man is riding a motorcycle on a road",
        "id": "6JnGBs88sL0_4_10.avi"
    },
    {
        "caption": "a man is jumping over and on a bed",
        "id": "EpMuCrbxE8A_107_115.avi"
    },
    {
        "caption": "a man is performing skating",
        "id": "HAjwXjwN9-A_16_24.avi"
    },
    {
        "caption": "a man is falling off his motorcycle",
        "id": "4xVGpDmA4lE_23_33.avi"
    },
    {
        "caption": "a man is riding a horse",
        "id": "k5OKBX2e7xA_19_32.avi"
    },
    {
        "caption": "a man is running on a road as a white truck emerges from behind and passes him",
        "id": "Jag7oTemldY_12_25.avi"
    },
    {
        "caption": "a man is playing a vegetable",
        "id": "8MVo7fje_oE_125_130.avi"
    },
    {
        "caption": "a woman is mixing flour in a bowl",
        "id": "bqMmyY1ImkI_0_14.avi"
    },
    {
        "caption": "a woman is peeling a potato",
        "id": "jTnrm338_KY_34_42.avi"
    },
    {
        "caption": "a man is riding a bicycle with training wheels in circles",
        "id": "UdcObAQ5OOM_15_30.avi"
    },
    {
        "caption": "a man is riding a small motor cycle on the edge of a road",
        "id": "4PcL6-mjRNk_11_18.avi"
    },
    {
        "caption": "a baby is getting sleepy while sitting",
        "id": "3qqEKTPxLNs_1_15.avi"
    },
    {
        "caption": "a woman is eating",
        "id": "glrijRGnmc0_211_215.avi"
    },
    {
        "caption": "a man and woman are riding a motorcycle",
        "id": "q7pOFn8s4zc_263_273.avi"
    },
    {
        "caption": "a woman is cutting a pepper",
        "id": "mtrCf667KDk_134_176.avi"
    },
    {
        "caption": "a woman is mixing an egg in a bowl",
        "id": "0lh_UWF9ZP4_62_69.avi"
    },
    {
        "caption": "a man is hitchhiking",
        "id": "JntMAcTlOF0_50_70.avi"
    },
    {
        "caption": "a man is singing and playing guitar",
        "id": "7NNg0_n-bS8_21_30.avi"
    },
    {
        "caption": "a woman is cutting shrimp lengthwise in half",
        "id": "IhwPQL9dFYc_124_129.avi"
    },
    {
        "caption": "a man is singing",
        "id": "BAf3LXFUaGs_28_38.avi"
    },
    {
        "caption": "a woman is singing",
        "id": "6q1dX6thX3E_286_295.avi"
    },
    {
        "caption": "a man is adding something to a bowl",
        "id": "RZL9irxnhZ0_34_40.avi"
    },
    {
        "caption": "a man is crashing his bike",
        "id": "WWf0Z6ak3Dg_5_15.avi"
    },
    {
        "caption": "a woman is cutting a potato",
        "id": "PeUHy0A1GF0_114_121.avi"
    },
    {
        "caption": "a man is kicking hanging pots",
        "id": "klteYv1Uv9A_27_33.avi"
    },
    {
        "caption": "a man is putting pork chops in a pan",
        "id": "e-j59PqJjSM_405_416.avi"
    },
    {
        "caption": "a red car explodes in a field",
        "id": "778mkceE0UQ_40_46.avi"
    },
    {
        "caption": "a man is riding a horse",
        "id": "77iDIp40m9E_126_131.avi"
    },
    {
        "caption": "a man is slicing onion",
        "id": "e-j59PqJjSM_50_98.avi"
    },
    {
        "caption": "a frog is biting a finger",
        "id": "Dgf0VHMEtNs_57_66.avi"
    },
    {
        "caption": "a dog is running down the sidewalk",
        "id": "f9Won2JpOEU_60_80.avi"
    },
    {
        "caption": "a car is driving",
        "id": "dfOuTx66bJU_34_39.avi"
    },
    {
        "caption": "a man is slicing a whole peeled garlic into fine pieces",
        "id": "04Gt01vatkk_248_265.avi"
    },
    {
        "caption": "a woman is practicing volleyball serves on the beach",
        "id": "rl1rVk_xIOs_1_16.avi"
    }
]